sequence-detector-moore-DE10-Lite/quartus_moore.vhd
library ieee;
use ieee.std_logic_1164.all;

entity quartus_moore is
   port (
      KEY    : in std_logic_vector(1 downto 0); 
      SW     : in std_logic_vector(1 downto 0);
      LEDR   : out std_logic_vector(2 downto 0);
      HEX0   : out std_logic_vector(6 downto 0);
      HEX1   : out std_logic_vector(6 downto 0);
      HEX2   : out std_logic_vector(6 downto 0);
      HEX3   : out std_logic_vector(6 downto 0);
      HEX4   : out std_logic_vector(6 downto 0);
      HEX5   : out std_logic_vector(6 downto 0);
		Z      : out std_logic
   );

end quartus_moore;

architecture process_3 of quartus_moore is
   type state_type is (A, B, C, D, E);
   signal state : state_type := A;
   signal x : std_logic := '0';
   signal reset : std_logic := '0';
begin

   input_control: process (KEY(0), KEY(1))
		variable tmp: std_logic := '0';
		begin
			if KEY(1) = '0' then
				state <= A;
			elsif rising_edge(KEY(0)) then
				tmp := SW(0);
				
				case state is
					when A =>
						if tmp = '1' then
							state <= B;
						else
							state <= A;
						end if;
					when B =>
						if tmp = '1' then
							state <= C;
						else
							state <= A;
						end if;
					when C =>
						if tmp = '1' then
							state <= C;
						else
							state <= D;
						end if;
					when D =>
						if tmp = '1' then
							state <= E;
						else
							state <= A;
						end if;
					when E =>
						if tmp = '1' then
							state <= C;
						else
							state <= A;
						end if;
				end case;
			end if;
		end process;

   -- Process: 7-segment display control for HEX0 to HEX5
   seg7_control: process(state)
   begin
      if state = E then
         HEX5 <= "1111001"; -- 1
         HEX4 <= "1111111"; -- blank
         HEX3 <= "1111111"; -- blank
         HEX2 <= "1111111"; -- blank
         HEX1 <= "1111111"; -- blank
         HEX0 <= "0000110"; -- E
      elsif state = D then
         HEX5 <= "1000000"; -- 0
         HEX4 <= "1111111"; -- blank
         HEX3 <= "1111111"; -- blank
         HEX2 <= "1111111"; -- blank
         HEX1 <= "1111111"; -- blank
         HEX0 <= "0100001"; -- D
		elsif state = C then
         HEX5 <= "1000000"; -- 0
         HEX4 <= "1111111"; -- blank
         HEX3 <= "1111111"; -- blank
         HEX2 <= "1111111"; -- blank
         HEX1 <= "1111111"; -- blank
         HEX0 <= "1000110"; -- C
		elsif state = B then
         HEX5 <= "1000000"; -- 0
         HEX4 <= "1111111"; -- blank
         HEX3 <= "1111111"; -- blank
         HEX2 <= "1111111"; -- blank
         HEX1 <= "1111111"; -- blank
         HEX0 <= "0000011"; -- b
		else
         HEX5 <= "1000000"; -- 0
         HEX4 <= "1111111"; -- blank
         HEX3 <= "1111111"; -- blank
         HEX2 <= "1111111"; -- blank
         HEX1 <= "1111111"; -- blank
         HEX0 <= "0001000"; -- A
      end if;
   end process;
   
	
   output_func: process (state)
   begin
      case state is
         when E =>
            Z <= '1';
         when others =>
            Z <= '0';
      end case;
   end process;
	
end process_3;

sequence-detector-moore-DE10-Lite/quartus_moore_testbench.vhd
-- Testbench for quartus_moore - Sequence Detector
library ieee;
use ieee.std_logic_1164.all;

entity quartus_moore_testbench is
end quartus_moore_testbench;

architecture tb_arch of quartus_moore_testbench is
   signal KEY  : std_logic_vector(1 downto 0);
   signal SW   : std_logic_vector(1 downto 0);
   signal LEDR : std_logic_vector(2 downto 0);
   signal Z    : std_logic;
begin

   -- Instantiate the Unit Under Test (UUT)
   uut: entity work.quartus_moore(process_3)
      port map (
         KEY  => KEY,
         SW   => SW,
         LEDR => LEDR,
         HEX0 => open,
         HEX1 => open,
         HEX2 => open,
         HEX3 => open,
         HEX4 => open,
         HEX5 => open,
         Z    => Z
      );

   -- Stimulus process: generates test vectors

   stimulus_process: process
   begin
      -- Initialize
      KEY(1) <= '0'; -- Assert reset
      KEY <= "11";
      SW <= "00";
      wait for 10 ns;

      KEY(1) <= '1'; -- Deassert reset
      wait for 10 ns;

      -- Send bit sequence: 1 1 0 1 -> should detect 1101 → Z='1'

      SW(0) <= '1'; wait for 10 ns;      
      KEY(0) <= '0'; wait for 10 ns; -- Rising edge
      KEY(0) <= '1'; wait for 10 ns; -- Falling edge

      KEY(0) <= '0'; wait for 10 ns; -- Rising edge
      KEY(0) <= '1'; wait for 10 ns; -- Falling edge

      SW(0) <= '0'; wait for 10 ns;      

      KEY(0) <= '0'; wait for 10 ns; -- Rising edge
      KEY(0) <= '1'; wait for 10 ns; -- Falling edge

      SW(0) <= '1'; wait for 10 ns;      

      KEY(0) <= '0'; wait for 10 ns; -- Rising edge
      KEY(0) <= '1'; wait for 10 ns; -- Falling edge

      -- now we already have 1 from the last sequence, so let add 1 0 1 to detect again
      SW(0) <= '1'; wait for 10 ns;      
      KEY(0) <= '0'; wait for 10 ns; -- Rising edge
      KEY(0) <= '1'; wait for 10 ns; -- Falling edge

      SW(0) <= '0'; wait for 10 ns;      
      KEY(0) <= '0'; wait for 10 ns; -- Rising edge
      KEY(0) <= '1'; wait for 10 ns; -- Falling edge

      SW(0) <= '1'; wait for 10 ns;      
      KEY(0) <= '0'; wait for 10 ns; -- Rising edge
      KEY(0) <= '1'; wait for 10 ns; -- Falling edge
     
      -- now a wrong sequence, so let add 0 1 1
      SW(0) <= '0'; wait for 10 ns;      
      KEY(0) <= '0'; wait for 10 ns; -- Rising edge
      KEY(0) <= '1'; wait for 10 ns; -- Falling edge

      SW(0) <= '1'; wait for 10 ns;      
      KEY(0) <= '0'; wait for 10 ns; -- Rising edge
      KEY(0) <= '1'; wait for 10 ns; -- Falling edge

      SW(0) <= '1'; wait for 10 ns;      
      KEY(0) <= '0'; wait for 10 ns; -- Rising edge
      KEY(0) <= '1'; wait for 10 ns; -- Falling edge
     
      wait;
   end process;

end tb_arch;

sequence-detector-moore-DE10-Lite/resposta.vcd
$date
  Mon Aug  4 21:57:43 2025
$end
$version
  GHDL v0
$end
$timescale
  1 fs
$end
$scope module standard $end
$upscope $end
$scope module std_logic_1164 $end
$upscope $end
$scope module quartus_moore_testbench $end
$var reg 2 ! key[1:0] $end
$var reg 2 " sw[1:0] $end
$var reg 3 # ledr[2:0] $end
$var reg 1 $ z $end
$scope module uut $end
$var reg 2 % key[1:0] $end
$var reg 2 & sw[1:0] $end
$var reg 3 ' ledr[2:0] $end
$var reg 7 ( hex0[6:0] $end
$var reg 7 ) hex1[6:0] $end
$var reg 7 * hex2[6:0] $end
$var reg 7 + hex3[6:0] $end
$var reg 7 , hex4[6:0] $end
$var reg 7 - hex5[6:0] $end
$var reg 1 . z $end
$comment state is not handled $end
$var reg 1 / x $end
$var reg 1 0 reset $end
$upscope $end
$upscope $end
$enddefinitions $end
#0
b11 !
b00 "
bUUU #
0$
b11 %
b00 &
bUUU '
b0001000 (
b1111111 )
b1111111 *
b1111111 +
b1111111 ,
b1000000 -
0.
0/
00
#10000000
#20000000
b01 "
b01 &
#30000000
b10 !
b10 %
#40000000
b11 !
b11 %
b0000011 (
#50000000
b10 !
b10 %
#60000000
b11 !
b11 %
b1000110 (
#70000000
b00 "
b00 &
#80000000
b10 !
b10 %
#90000000
b11 !
b11 %
b0100001 (
#100000000
b01 "
b01 &
#110000000
b10 !
b10 %
#120000000
b11 !
1$
b11 %
b0000110 (
b1111001 -
1.
#130000000
#140000000
b10 !
b10 %
#150000000
b11 !
0$
b11 %
b1000110 (
b1000000 -
0.
#160000000
b00 "
b00 &
#170000000
b10 !
b10 %
#180000000
b11 !
b11 %
b0100001 (
#190000000
b01 "
b01 &
#200000000
b10 !
b10 %
#210000000
b11 !
1$
b11 %
b0000110 (
b1111001 -
1.
#220000000
b00 "
b00 &
#230000000
b10 !
b10 %
#240000000
b11 !
0$
b11 %
b0001000 (
b1000000 -
0.
#250000000
b01 "
b01 &
#260000000
b10 !
b10 %
#270000000
b11 !
b11 %
b0000011 (
#280000000
#290000000
b10 !
b10 %
#300000000
b11 !
b11 %
b1000110 (
